Metadata-Version: 1.0
Name: tinyjenkins
Version: 0.0.1
Summary: A tiny jenkins client library
Home-page: UNKNOWN
Author: Josh Harlow
Author-email: harlowja@gmail.com
License: ASL
Keywords: jenkins
Platform: UNKNOWN
